{"_id":"cluster","_rev":"105-d789e58c79cda9a8edc9c2a9e172d477","name":"cluster","description":"extensible multi-core server manager","dist-tags":{"latest":"0.7.7"},"versions":{"0.0.1":{"name":"cluster","description":"extensible multi-core server manager","keywords":["server","spark","fugue"],"version":"0.0.1","homepage":"http://learnboost.github.com/cluster","repository":"git://github.com/LearnBoost/cluster.git","author":{"name":"TJ Holowaychuk","email":"tj@learnboost.com","url":"http://tjholowaychuk.com"},"main":"index","engines":{"node":"*"},"_id":"cluster@0.0.1","_engineSupported":true,"_npmVersion":"0.2.16","_nodeVersion":"v0.2.6","directories":{"lib":"./lib"},"modules":{"cluster.js":"lib/cluster.js","master.js":"lib/master.js","utils.js":"lib/utils.js","worker.js":"lib/worker.js","mixins/receiver.js":"lib/mixins/receiver.js","plugins/cli.js":"lib/plugins/cli.js","plugins/debug.js":"lib/plugins/debug.js","plugins/logger.js":"lib/plugins/logger.js","plugins/pidfiles.js":"lib/plugins/pidfiles.js","plugins/reload.js":"lib/plugins/reload.js","plugins/repl.js":"lib/plugins/repl.js","plugins/stats.js":"lib/plugins/stats.js"},"files":[""],"_defaultsLoaded":true,"dist":{"shasum":"4b983fb2749683136a323c99bf99d0c7653f2272","tarball":"https://registry.npmjs.org/cluster/-/cluster-0.0.1.tgz"}},"0.0.2":{"name":"cluster","description":"extensible multi-core server manager","keywords":["server","spark","fugue"],"version":"0.0.2","homepage":"http://learnboost.github.com/cluster","repository":"git://github.com/LearnBoost/cluster.git","author":{"name":"TJ Holowaychuk","email":"tj@learnboost.com","url":"http://tjholowaychuk.com"},"main":"index","engines":{"node":"*"},"_id":"cluster@0.0.2","_engineSupported":true,"_npmVersion":"0.2.16","_nodeVersion":"v0.2.6","directories":{"lib":"./lib"},"modules":{"cluster.js":"lib/cluster.js","master.js":"lib/master.js","utils.js":"lib/utils.js","worker.js":"lib/worker.js","mixins/receiver.js":"lib/mixins/receiver.js","plugins/cli.js":"lib/plugins/cli.js","plugins/debug.js":"lib/plugins/debug.js","plugins/logger.js":"lib/plugins/logger.js","plugins/pidfiles.js":"lib/plugins/pidfiles.js","plugins/reload.js":"lib/plugins/reload.js","plugins/repl.js":"lib/plugins/repl.js","plugins/stats.js":"lib/plugins/stats.js"},"files":[""],"_defaultsLoaded":true,"dist":{"shasum":"f5bea19a83aa195015a079a185526e800b580487","tarball":"https://registry.npmjs.org/cluster/-/cluster-0.0.2.tgz"}},"0.0.3":{"name":"cluster","description":"extensible multi-core server manager","keywords":["server","spark","fugue"],"version":"0.0.3","homepage":"http://learnboost.github.com/cluster","repository":"git://github.com/LearnBoost/cluster.git","author":{"name":"TJ Holowaychuk","email":"tj@learnboost.com","url":"http://tjholowaychuk.com"},"main":"index","dependencies":{"log":">= 1.1.1"},"engines":{"node":"*"},"_id":"cluster@0.0.3","_engineSupported":true,"_npmVersion":"0.2.16","_nodeVersion":"v0.2.6","directories":{"lib":"./lib"},"modules":{"cluster.js":"lib/cluster.js","master.js":"lib/master.js","utils.js":"lib/utils.js","worker.js":"lib/worker.js","mixins/receiver.js":"lib/mixins/receiver.js","plugins/cli.js":"lib/plugins/cli.js","plugins/debug.js":"lib/plugins/debug.js","plugins/logger.js":"lib/plugins/logger.js","plugins/pidfiles.js":"lib/plugins/pidfiles.js","plugins/reload.js":"lib/plugins/reload.js","plugins/repl.js":"lib/plugins/repl.js","plugins/stats.js":"lib/plugins/stats.js"},"files":[""],"_defaultsLoaded":true,"dist":{"shasum":"c3bfbcf25ebb026fe0bec37106e0632885c0f0d0","tarball":"https://registry.npmjs.org/cluster/-/cluster-0.0.3.tgz"}},"0.0.4":{"name":"cluster","description":"extensible multi-core server manager","keywords":["server","spark","fugue"],"version":"0.0.4","homepage":"http://learnboost.github.com/cluster","repository":"git://github.com/LearnBoost/cluster.git","author":{"name":"TJ Holowaychuk","email":"tj@learnboost.com","url":"http://tjholowaychuk.com"},"main":"index","dependencies":{"log":">= 1.1.1"},"engines":{"node":"*"},"_id":"cluster@0.0.4","_engineSupported":true,"_npmVersion":"0.2.18","_nodeVersion":"v0.2.6","directories":{"lib":"./lib"},"files":[""],"_defaultsLoaded":true,"dist":{"shasum":"67dcb6077167224d97fb86bfacf9108ced164ad7","tarball":"https://registry.npmjs.org/cluster/-/cluster-0.0.4.tgz"}},"0.1.0":{"name":"cluster","description":"extensible multi-core server manager","keywords":["server","spark","fugue","tcp","workers"],"version":"0.1.0","homepage":"http://learnboost.github.com/cluster","repository":"git://github.com/LearnBoost/cluster.git","author":{"name":"TJ Holowaychuk","email":"tj@learnboost.com","url":"http://tjholowaychuk.com"},"main":"index","dependencies":{"log":">= 1.1.1"},"engines":{"node":"*"},"_id":"cluster@0.1.0","_engineSupported":true,"_npmVersion":"0.2.18","_nodeVersion":"v0.4.0","directories":{"lib":"./lib"},"files":[""],"_defaultsLoaded":true,"dist":{"shasum":"6ee865dc7719a069682a444c62516fbe233073e4","tarball":"https://registry.npmjs.org/cluster/-/cluster-0.1.0.tgz"}},"0.1.1":{"name":"cluster","description":"extensible multi-core server manager","keywords":["server","spark","fugue","tcp","workers"],"version":"0.1.1","homepage":"http://learnboost.github.com/cluster","repository":"git://github.com/LearnBoost/cluster.git","author":{"name":"TJ Holowaychuk","email":"tj@learnboost.com","url":"http://tjholowaychuk.com"},"main":"index","dependencies":{"log":">= 1.1.1"},"engines":{"node":"*"},"_id":"cluster@0.1.1","_engineSupported":true,"_npmVersion":"0.2.18","_nodeVersion":"v0.2.6","directories":{"lib":"./lib"},"files":[""],"_defaultsLoaded":true,"dist":{"shasum":"7aebc8d80a6a89f64a18934e689e228d91ceb22b","tarball":"https://registry.npmjs.org/cluster/-/cluster-0.1.1.tgz"}},"0.2.0":{"name":"cluster","description":"extensible multi-core server manager","keywords":["server","spark","fugue","tcp","workers"],"version":"0.2.0","homepage":"http://learnboost.github.com/cluster","repository":"git://github.com/LearnBoost/cluster.git","author":{"name":"TJ Holowaychuk","email":"tj@learnboost.com","url":"http://tjholowaychuk.com"},"main":"index","dependencies":{"log":">= 1.1.1"},"engines":{"node":"*"},"_id":"cluster@0.2.0","_engineSupported":true,"_npmVersion":"0.2.18","_nodeVersion":"v0.2.6","directories":{"lib":"./lib"},"files":[""],"_defaultsLoaded":true,"dist":{"shasum":"94b06f9f25175c8c3129a9c701acb5144d2bda56","tarball":"https://registry.npmjs.org/cluster/-/cluster-0.2.0.tgz"}},"0.2.1":{"name":"cluster","description":"extensible multi-core server manager","keywords":["server","spark","fugue","tcp","workers"],"version":"0.2.1","homepage":"http://learnboost.github.com/cluster","repository":"git://github.com/LearnBoost/cluster.git","author":{"name":"TJ Holowaychuk","email":"tj@learnboost.com","url":"http://tjholowaychuk.com"},"main":"index","dependencies":{"log":">= 1.1.1"},"engines":{"node":"*"},"_id":"cluster@0.2.1","_engineSupported":true,"_npmVersion":"0.2.18","_nodeVersion":"v0.2.6","directories":{"lib":"./lib"},"files":[""],"_defaultsLoaded":true,"dist":{"shasum":"bb4b46f02da8ccaff8bd3846b360884a21dfda43","tarball":"https://registry.npmjs.org/cluster/-/cluster-0.2.1.tgz"}},"0.2.2":{"name":"cluster","description":"extensible multi-core server manager","keywords":["server","spark","fugue","tcp","workers"],"version":"0.2.2","homepage":"http://learnboost.github.com/cluster","repository":"git://github.com/LearnBoost/cluster.git","author":{"name":"TJ Holowaychuk","email":"tj@learnboost.com","url":"http://tjholowaychuk.com"},"main":"index","dependencies":{"log":">= 1.1.1"},"engines":{"node":"*"},"_id":"cluster@0.2.2","_engineSupported":true,"_npmVersion":"0.2.18","_nodeVersion":"v0.4.1","directories":{"lib":"./lib"},"files":[""],"_defaultsLoaded":true,"dist":{"shasum":"583634e2c4cdd8faea4357c55e9bd2c25d6e2b42","tarball":"https://registry.npmjs.org/cluster/-/cluster-0.2.2.tgz"}},"0.2.3":{"name":"cluster","description":"extensible multi-core server manager","keywords":["server","spark","fugue","tcp","workers"],"version":"0.2.3","homepage":"http://learnboost.github.com/cluster","repository":"git://github.com/LearnBoost/cluster.git","author":{"name":"TJ Holowaychuk","email":"tj@learnboost.com","url":"http://tjholowaychuk.com"},"main":"index","dependencies":{"log":">= 1.1.1"},"engines":{"node":"*"},"_id":"cluster@0.2.3","_engineSupported":true,"_npmVersion":"0.2.18","_nodeVersion":"v0.4.1","directories":{"lib":"./lib"},"files":[""],"_defaultsLoaded":true,"dist":{"shasum":"3209e03f5497ca01ff8a03da8eb76b8c74dc4b3b","tarball":"https://registry.npmjs.org/cluster/-/cluster-0.2.3.tgz"}},"0.2.4":{"name":"cluster","description":"extensible multi-core server manager","keywords":["server","spark","fugue","tcp","workers"],"version":"0.2.4","homepage":"http://learnboost.github.com/cluster","repository":"git://github.com/LearnBoost/cluster.git","author":{"name":"TJ Holowaychuk","email":"tj@learnboost.com","url":"http://tjholowaychuk.com"},"main":"index","dependencies":{"log":">= 1.1.1"},"engines":{"node":"*"},"_id":"cluster@0.2.4","_engineSupported":true,"_npmVersion":"0.2.18","_nodeVersion":"v0.4.1","directories":{"lib":"./lib"},"files":[""],"_defaultsLoaded":true,"dist":{"shasum":"fec9eb44b63f16dee1992474e60de9e887b65bcf","tarball":"https://registry.npmjs.org/cluster/-/cluster-0.2.4.tgz"}},"0.3.0":{"name":"cluster","description":"extensible multi-core server manager","keywords":["server","spark","fugue","tcp","workers"],"version":"0.3.0","homepage":"http://learnboost.github.com/cluster","repository":"git://github.com/LearnBoost/cluster.git","author":{"name":"TJ Holowaychuk","email":"tj@learnboost.com","url":"http://tjholowaychuk.com"},"main":"index","dependencies":{"log":">= 1.1.1"},"engines":{"node":"*"},"_id":"cluster@0.3.0","_engineSupported":true,"_npmVersion":"0.2.18","_nodeVersion":"v0.4.1","directories":{"lib":"./lib"},"files":[""],"_defaultsLoaded":true,"dist":{"shasum":"266527276c820afab652350d2bea2b569c1cb616","tarball":"https://registry.npmjs.org/cluster/-/cluster-0.3.0.tgz"}},"0.3.1":{"name":"cluster","description":"extensible multi-core server manager","keywords":["server","spark","fugue","tcp","workers"],"version":"0.3.1","homepage":"http://learnboost.github.com/cluster","repository":"git://github.com/LearnBoost/cluster.git","author":{"name":"TJ Holowaychuk","email":"tj@learnboost.com","url":"http://tjholowaychuk.com"},"main":"index","dependencies":{"log":">= 1.1.1"},"engines":{"node":"*"},"_id":"cluster@0.3.1","_engineSupported":true,"_npmVersion":"0.2.18","_nodeVersion":"v0.4.1","directories":{"lib":"./lib"},"files":[""],"_defaultsLoaded":true,"dist":{"shasum":"bd210242af35772c151b21ac0299cf72b35f2c2f","tarball":"https://registry.npmjs.org/cluster/-/cluster-0.3.1.tgz"}},"0.3.2":{"name":"cluster","description":"extensible multi-core server manager","keywords":["server","spark","fugue","tcp","workers"],"version":"0.3.2","homepage":"http://learnboost.github.com/cluster","repository":{"type":"git","url":"git://github.com/LearnBoost/cluster.git"},"author":{"name":"TJ Holowaychuk","email":"tj@learnboost.com","url":"http://tjholowaychuk.com"},"main":"index","dependencies":{"log":">= 1.1.1"},"engines":{"node":"*"},"_id":"cluster@0.3.2","_engineSupported":true,"_npmVersion":"0.3.11","_nodeVersion":"v0.4.1","directories":{"lib":"./lib"},"files":[""],"_defaultsLoaded":true,"dist":{"shasum":"3ea173beefbbf2b80145c3d60775032f9c135ab4","tarball":"https://registry.npmjs.org/cluster/-/cluster-0.3.2.tgz"}},"0.3.3":{"name":"cluster","description":"extensible multi-core server manager","keywords":["server","spark","fugue","tcp","workers"],"version":"0.3.3","homepage":"http://learnboost.github.com/cluster","repository":{"type":"git","url":"git://github.com/LearnBoost/cluster.git"},"author":{"name":"TJ Holowaychuk","email":"tj@learnboost.com","url":"http://tjholowaychuk.com"},"main":"index","dependencies":{"log":">= 1.1.1"},"engines":{"node":"*"},"_id":"cluster@0.3.3","_engineSupported":true,"_npmVersion":"0.3.13","_nodeVersion":"v0.4.2","directories":{"lib":"./lib"},"files":[""],"_defaultsLoaded":true,"dist":{"shasum":"37de66970874e666bb61fe1ea3cf9958d929d935","tarball":"https://registry.npmjs.org/cluster/-/cluster-0.3.3.tgz"}},"0.4.0":{"name":"cluster","description":"extensible multi-core server manager","keywords":["server","spark","fugue","tcp","workers"],"version":"0.4.0","homepage":"http://learnboost.github.com/cluster","repository":{"type":"git","url":"git://github.com/LearnBoost/cluster.git"},"author":{"name":"TJ Holowaychuk","email":"tj@learnboost.com","url":"http://tjholowaychuk.com"},"main":"index","dependencies":{"log":">= 1.1.1"},"engines":{"node":"*"},"_id":"cluster@0.4.0","_engineSupported":true,"_npmVersion":"0.3.15","_nodeVersion":"v0.4.2","directories":{"lib":"./lib"},"files":[""],"_defaultsLoaded":true,"dist":{"shasum":"b32903346dc6470d10a7e1c2475ab3cd23408414","tarball":"https://registry.npmjs.org/cluster/-/cluster-0.4.0.tgz"}},"0.4.1":{"name":"cluster","description":"extensible multi-core server manager","keywords":["server","spark","fugue","tcp","workers"],"version":"0.4.1","homepage":"http://learnboost.github.com/cluster","repository":{"type":"git","url":"git://github.com/LearnBoost/cluster.git"},"author":{"name":"TJ Holowaychuk","email":"tj@learnboost.com","url":"http://tjholowaychuk.com"},"main":"index","dependencies":{"log":">= 1.1.1"},"engines":{"node":"*"},"_id":"cluster@0.4.1","_engineSupported":true,"_npmVersion":"0.3.15","_nodeVersion":"v0.4.2","directories":{"lib":"./lib"},"files":[""],"_defaultsLoaded":true,"dist":{"shasum":"3dafe0fac58ed417c076c28126e3c2f15f071ee1","tarball":"https://registry.npmjs.org/cluster/-/cluster-0.4.1.tgz"}},"0.4.2":{"name":"cluster","description":"extensible multi-core server manager","keywords":["server","spark","fugue","tcp","workers"],"version":"0.4.2","homepage":"http://learnboost.github.com/cluster","repository":{"type":"git","url":"git://github.com/LearnBoost/cluster.git"},"author":{"name":"TJ Holowaychuk","email":"tj@learnboost.com","url":"http://tjholowaychuk.com"},"main":"index","dependencies":{"log":">= 1.1.1"},"engines":{"node":"*"},"_id":"cluster@0.4.2","_engineSupported":true,"_npmVersion":"0.3.15","_nodeVersion":"v0.4.2","directories":{"lib":"./lib"},"files":[""],"_defaultsLoaded":true,"dist":{"shasum":"660fb86f4eef654d128087ee25ea3830e058a44e","tarball":"https://registry.npmjs.org/cluster/-/cluster-0.4.2.tgz"}},"0.5.0":{"name":"cluster","description":"extensible multi-core server manager","keywords":["server","spark","fugue","tcp","workers"],"version":"0.5.0","homepage":"http://learnboost.github.com/cluster","repository":{"type":"git","url":"git://github.com/LearnBoost/cluster.git"},"author":{"name":"TJ Holowaychuk","email":"tj@learnboost.com","url":"http://tjholowaychuk.com"},"main":"index","dependencies":{"log":">= 1.1.1"},"engines":{"node":"*"},"_id":"cluster@0.5.0","_engineSupported":true,"_npmVersion":"0.3.15","_nodeVersion":"v0.4.3","directories":{"lib":"./lib"},"files":[""],"_defaultsLoaded":true,"dist":{"shasum":"45d13762f06029b8477f7316d3f6189ac970aafb","tarball":"https://registry.npmjs.org/cluster/-/cluster-0.5.0.tgz"}},"0.5.1":{"name":"cluster","description":"extensible multi-core server manager","keywords":["server","spark","fugue","tcp","workers"],"version":"0.5.1","homepage":"http://learnboost.github.com/cluster","repository":{"type":"git","url":"git://github.com/LearnBoost/cluster.git"},"author":{"name":"TJ Holowaychuk","email":"tj@learnboost.com","url":"http://tjholowaychuk.com"},"main":"index","dependencies":{"log":">= 1.1.1"},"engines":{"node":"*"},"_id":"cluster@0.5.1","_engineSupported":true,"_npmVersion":"0.3.15","_nodeVersion":"v0.4.3","directories":{"lib":"./lib"},"files":[""],"_defaultsLoaded":true,"dist":{"shasum":"e09a5731d978dd60a37e9fe1d6b640e1450f5cfc","tarball":"https://registry.npmjs.org/cluster/-/cluster-0.5.1.tgz"}},"0.5.2":{"name":"cluster","description":"extensible multi-core server manager","keywords":["server","spark","fugue","tcp","workers"],"version":"0.5.2","homepage":"http://learnboost.github.com/cluster","repository":{"type":"git","url":"git://github.com/LearnBoost/cluster.git"},"author":{"name":"TJ Holowaychuk","email":"tj@learnboost.com","url":"http://tjholowaychuk.com"},"main":"index","dependencies":{"log":">= 1.1.1"},"engines":{"node":"*"},"_id":"cluster@0.5.2","_engineSupported":true,"_npmVersion":"0.3.15","_nodeVersion":"v0.4.3","directories":{"lib":"./lib"},"files":[""],"_defaultsLoaded":true,"dist":{"shasum":"a65470f04f945ea066d80e53e1e90e43203a89df","tarball":"https://registry.npmjs.org/cluster/-/cluster-0.5.2.tgz"}},"0.5.3":{"name":"cluster","description":"extensible multi-core server manager","keywords":["server","spark","fugue","tcp","workers"],"version":"0.5.3","homepage":"http://learnboost.github.com/cluster","repository":{"type":"git","url":"git://github.com/LearnBoost/cluster.git"},"author":{"name":"TJ Holowaychuk","email":"tj@learnboost.com","url":"http://tjholowaychuk.com"},"main":"index","dependencies":{"log":">= 1.1.1"},"engines":{"node":"*"},"_id":"cluster@0.5.3","_engineSupported":true,"_npmVersion":"0.3.15","_nodeVersion":"v0.4.3","directories":{"lib":"./lib"},"files":[""],"_defaultsLoaded":true,"dist":{"shasum":"e774cbb676b1458bfec4dc367b3e3c9a069cf09a","tarball":"https://registry.npmjs.org/cluster/-/cluster-0.5.3.tgz"}},"0.5.4":{"name":"cluster","description":"extensible multi-core server manager","keywords":["server","spark","fugue","tcp","workers"],"version":"0.5.4","homepage":"http://learnboost.github.com/cluster","repository":{"type":"git","url":"git://github.com/LearnBoost/cluster.git"},"author":{"name":"TJ Holowaychuk","email":"tj@learnboost.com","url":"http://tjholowaychuk.com"},"main":"index","dependencies":{"log":">= 1.1.1"},"engines":{"node":"*"},"_id":"cluster@0.5.4","_engineSupported":true,"_npmVersion":"0.3.15","_nodeVersion":"v0.4.4","directories":{"lib":"./lib"},"files":[""],"_defaultsLoaded":true,"dist":{"shasum":"e437d6ff65893f93309e7b718aef02ddb1ed522e","tarball":"https://registry.npmjs.org/cluster/-/cluster-0.5.4.tgz"}},"0.5.5":{"name":"cluster","description":"extensible multi-core server manager","keywords":["server","spark","fugue","tcp","workers"],"version":"0.5.5","homepage":"http://learnboost.github.com/cluster","repository":{"type":"git","url":"git://github.com/LearnBoost/cluster.git"},"author":{"name":"TJ Holowaychuk","email":"tj@learnboost.com","url":"http://tjholowaychuk.com"},"main":"index","dependencies":{"log":">= 1.1.1"},"engines":{"node":"*"},"_id":"cluster@0.5.5","_engineSupported":true,"_npmVersion":"0.3.15","_nodeVersion":"v0.4.4","directories":{"lib":"./lib"},"files":[""],"_defaultsLoaded":true,"dist":{"shasum":"579cc3eb12d20163c19cf97c090bf950d3c42be0","tarball":"https://registry.npmjs.org/cluster/-/cluster-0.5.5.tgz"}},"0.5.6":{"name":"cluster","description":"extensible multi-core server manager","keywords":["server","spark","fugue","tcp","workers"],"version":"0.5.6","homepage":"http://learnboost.github.com/cluster","repository":{"type":"git","url":"git://github.com/LearnBoost/cluster.git"},"author":{"name":"TJ Holowaychuk","email":"tj@learnboost.com","url":"http://tjholowaychuk.com"},"main":"index","dependencies":{"log":">= 1.1.1"},"engines":{"node":"*"},"_id":"cluster@0.5.6","_engineSupported":true,"_npmVersion":"0.3.18","_nodeVersion":"v0.4.6","directories":{"lib":"./lib"},"files":[""],"_defaultsLoaded":true,"dist":{"shasum":"cd61e985ef8a6dd77a38034f65a0273166e8df44","tarball":"https://registry.npmjs.org/cluster/-/cluster-0.5.6.tgz"}},"0.5.7":{"name":"cluster","description":"extensible multi-core server manager","keywords":["server","spark","fugue","tcp","workers"],"version":"0.5.7","homepage":"http://learnboost.github.com/cluster","repository":{"type":"git","url":"git://github.com/LearnBoost/cluster.git"},"author":{"name":"TJ Holowaychuk","email":"tj@learnboost.com","url":"http://tjholowaychuk.com"},"main":"index","dependencies":{"log":">= 1.1.1"},"engines":{"node":"*"},"_id":"cluster@0.5.7","_engineSupported":true,"_npmVersion":"0.3.18","_nodeVersion":"v0.4.6","directories":{"lib":"./lib"},"files":[""],"_defaultsLoaded":true,"dist":{"shasum":"71af43f3d9411733b8e0e4860a77c8a755de2326","tarball":"https://registry.npmjs.org/cluster/-/cluster-0.5.7.tgz"}},"0.6.0":{"name":"cluster","description":"extensible multi-core server manager","keywords":["server","spark","fugue","tcp","workers"],"version":"0.6.0","homepage":"http://learnboost.github.com/cluster","repository":{"type":"git","url":"git://github.com/LearnBoost/cluster.git"},"author":{"name":"TJ Holowaychuk","email":"tj@learnboost.com","url":"http://tjholowaychuk.com"},"main":"index","dependencies":{"log":">= 1.1.1"},"engines":{"node":"*"},"_id":"cluster@0.6.0","_engineSupported":true,"_npmVersion":"0.3.18","_nodeVersion":"v0.4.6","directories":{"lib":"./lib"},"files":[""],"_defaultsLoaded":true,"dist":{"shasum":"b6c3cd0b4a7d72f891323e173874949efd345820","tarball":"https://registry.npmjs.org/cluster/-/cluster-0.6.0.tgz"}},"0.6.1":{"name":"cluster","description":"extensible multi-core server manager","keywords":["server","spark","fugue","tcp","workers"],"version":"0.6.1","homepage":"http://learnboost.github.com/cluster","repository":{"type":"git","url":"git://github.com/LearnBoost/cluster.git"},"author":{"name":"TJ Holowaychuk","email":"tj@learnboost.com","url":"http://tjholowaychuk.com"},"main":"index","dependencies":{"log":">= 1.1.1"},"engines":{"node":"*"},"_id":"cluster@0.6.1","_engineSupported":true,"_npmVersion":"0.3.18","_nodeVersion":"v0.4.6","directories":{"lib":"./lib"},"files":[""],"_defaultsLoaded":true,"dist":{"shasum":"d02e41b543c9a2978f83d52602f4aa661f61b0b5","tarball":"https://registry.npmjs.org/cluster/-/cluster-0.6.1.tgz"}},"0.6.2":{"name":"cluster","description":"extensible multi-core server manager","keywords":["server","spark","fugue","tcp","workers"],"version":"0.6.2","homepage":"http://learnboost.github.com/cluster","repository":{"type":"git","url":"git://github.com/LearnBoost/cluster.git"},"author":{"name":"TJ Holowaychuk","email":"tj@learnboost.com","url":"http://tjholowaychuk.com"},"main":"index","dependencies":{"log":">= 1.1.1"},"devDependencies":{"should":"0.2.x"},"engines":{"node":"*"},"_id":"cluster@0.6.2","_engineSupported":true,"_npmVersion":"1.0.3","_nodeVersion":"v0.4.7","_defaultsLoaded":true,"dist":{"shasum":"0497cac4e174d529c44d9f2de273c93cc3dfa600","tarball":"https://registry.npmjs.org/cluster/-/cluster-0.6.2.tgz"},"scripts":{},"directories":{}},"0.6.3":{"name":"cluster","description":"extensible multi-core server manager","keywords":["server","spark","fugue","tcp","workers"],"version":"0.6.3","homepage":"http://learnboost.github.com/cluster","repository":{"type":"git","url":"git://github.com/LearnBoost/cluster.git"},"author":{"name":"TJ Holowaychuk","email":"tj@learnboost.com","url":"http://tjholowaychuk.com"},"main":"index","dependencies":{"log":">= 1.2.0"},"devDependencies":{"should":"0.2.x"},"engines":{"node":"*"},"_id":"cluster@0.6.3","_engineSupported":true,"_npmVersion":"1.0.3","_nodeVersion":"v0.4.8","_defaultsLoaded":true,"dist":{"shasum":"69c57156c20fafc6104398e16d6febd558fc2fbf","tarball":"https://registry.npmjs.org/cluster/-/cluster-0.6.3.tgz"},"scripts":{},"directories":{}},"0.6.4":{"name":"cluster","description":"extensible multi-core server manager","keywords":["server","spark","fugue","tcp","workers"],"version":"0.6.4","homepage":"http://learnboost.github.com/cluster","repository":{"type":"git","url":"git://github.com/LearnBoost/cluster.git"},"author":{"name":"TJ Holowaychuk","email":"tj@learnboost.com","url":"http://tjholowaychuk.com"},"main":"index","dependencies":{"log":">= 1.2.0"},"devDependencies":{"should":"0.2.x"},"engines":{"node":"*"},"_id":"cluster@0.6.4","_engineSupported":true,"_npmVersion":"1.0.3","_nodeVersion":"v0.4.8","_defaultsLoaded":true,"dist":{"shasum":"89bf11df5344642767089026d0101aaa0cf4f23e","tarball":"https://registry.npmjs.org/cluster/-/cluster-0.6.4.tgz"},"scripts":{},"directories":{}},"0.6.5":{"name":"cluster","description":"extensible multi-core server manager","keywords":["server","spark","fugue","tcp","workers"],"version":"0.6.5","homepage":"http://learnboost.github.com/cluster","repository":{"type":"git","url":"git://github.com/LearnBoost/cluster.git"},"author":{"name":"TJ Holowaychuk","email":"tj@learnboost.com","url":"http://tjholowaychuk.com"},"main":"index","dependencies":{"log":">= 1.2.0"},"devDependencies":{"should":"0.2.x"},"engines":{"node":"*"},"_npmJsonOpts":{"file":"/Users/tj/.npm/cluster/0.6.5/package/package.json","wscript":false,"contributors":false,"serverjs":false},"_id":"cluster@0.6.5","_engineSupported":true,"_npmVersion":"1.0.14","_nodeVersion":"v0.4.9","_defaultsLoaded":true,"dist":{"shasum":"a6eb0e32060426ae92ee44b4d165ebdc67e198e3","tarball":"https://registry.npmjs.org/cluster/-/cluster-0.6.5.tgz"},"scripts":{},"directories":{}},"0.6.6":{"name":"cluster","description":"extensible multi-core server manager","keywords":["server","spark","fugue","tcp","workers"],"version":"0.6.6","homepage":"http://learnboost.github.com/cluster","repository":{"type":"git","url":"git://github.com/LearnBoost/cluster.git"},"author":{"name":"TJ Holowaychuk","email":"tj@learnboost.com","url":"http://tjholowaychuk.com"},"main":"index","dependencies":{"log":">= 1.2.0"},"devDependencies":{"should":"0.2.x"},"engines":{"node":"*"},"_npmJsonOpts":{"file":"/Users/tj/.npm/cluster/0.6.6/package/package.json","wscript":false,"contributors":false,"serverjs":false},"_id":"cluster@0.6.6","_engineSupported":true,"_npmVersion":"1.0.14","_nodeVersion":"v0.4.9","_defaultsLoaded":true,"dist":{"shasum":"672c82345e30f989c3e415c38738ab8261ffed9f","tarball":"https://registry.npmjs.org/cluster/-/cluster-0.6.6.tgz"},"scripts":{},"directories":{}},"0.6.7":{"name":"cluster","description":"extensible multi-core server manager","keywords":["server","spark","fugue","tcp","workers"],"version":"0.6.7","homepage":"http://learnboost.github.com/cluster","repository":{"type":"git","url":"git://github.com/LearnBoost/cluster.git"},"author":{"name":"TJ Holowaychuk","email":"tj@learnboost.com","url":"http://tjholowaychuk.com"},"main":"index","dependencies":{"log":">= 1.2.0"},"devDependencies":{"should":"0.2.x"},"engines":{"node":"*"},"_npmJsonOpts":{"file":"/Users/tj/.npm/cluster/0.6.7/package/package.json","wscript":false,"contributors":false,"serverjs":false},"_id":"cluster@0.6.7","_engineSupported":true,"_npmVersion":"1.0.14","_nodeVersion":"v0.4.9","_defaultsLoaded":true,"dist":{"shasum":"90426ab7fd108e0e7bf3c871c2bbca851dba3b4a","tarball":"https://registry.npmjs.org/cluster/-/cluster-0.6.7.tgz"},"scripts":{},"directories":{}},"0.6.8":{"name":"cluster","description":"extensible multi-core server manager","keywords":["server","spark","fugue","tcp","workers"],"version":"0.6.8","homepage":"http://learnboost.github.com/cluster","repository":{"type":"git","url":"git://github.com/LearnBoost/cluster.git"},"author":{"name":"TJ Holowaychuk","email":"tj@learnboost.com","url":"http://tjholowaychuk.com"},"main":"index","dependencies":{"log":">= 1.2.0"},"devDependencies":{"should":"0.2.x"},"engines":{"node":"*"},"_npmJsonOpts":{"file":"/Users/tj/.npm/cluster/0.6.8/package/package.json","wscript":false,"contributors":false,"serverjs":false},"_id":"cluster@0.6.8","_engineSupported":true,"_npmVersion":"1.0.14","_nodeVersion":"v0.4.9","_defaultsLoaded":true,"dist":{"shasum":"87c55f2b0665bde2b44f9de309b82fe1dd74c043","tarball":"https://registry.npmjs.org/cluster/-/cluster-0.6.8.tgz"},"scripts":{},"directories":{}},"0.6.9":{"name":"cluster","description":"extensible multi-core server manager","keywords":["server","spark","fugue","tcp","workers"],"version":"0.6.9","homepage":"http://learnboost.github.com/cluster","repository":{"type":"git","url":"git://github.com/LearnBoost/cluster.git"},"author":{"name":"TJ Holowaychuk","email":"tj@learnboost.com","url":"http://tjholowaychuk.com"},"main":"index","dependencies":{"log":">= 1.2.0"},"devDependencies":{"should":"0.2.x"},"engines":{"node":"*"},"_npmJsonOpts":{"file":"/Users/tj/.npm/cluster/0.6.9/package/package.json","wscript":false,"contributors":false,"serverjs":false},"_id":"cluster@0.6.9","_engineSupported":true,"_npmVersion":"1.0.14","_nodeVersion":"v0.4.9","_defaultsLoaded":true,"dist":{"shasum":"6de31ceba5c976fe69adca2ca88620a4fc25f60f","tarball":"https://registry.npmjs.org/cluster/-/cluster-0.6.9.tgz"},"scripts":{},"directories":{}},"0.7.0":{"name":"cluster","description":"extensible multi-core server manager","keywords":["server","spark","fugue","tcp","workers"],"version":"0.7.0","homepage":"http://learnboost.github.com/cluster","repository":{"type":"git","url":"git://github.com/LearnBoost/cluster.git"},"author":{"name":"TJ Holowaychuk","email":"tj@learnboost.com","url":"http://tjholowaychuk.com"},"main":"index","dependencies":{"log":">= 1.2.0","mkdirp":">= 0.0.1"},"devDependencies":{"should":"0.2.x"},"engines":{"node":"*"},"_npmJsonOpts":{"file":"/Users/tj/.npm/cluster/0.7.0/package/package.json","wscript":false,"contributors":false,"serverjs":false},"_id":"cluster@0.7.0","_engineSupported":true,"_npmVersion":"1.0.24","_nodeVersion":"v0.4.10","_defaultsLoaded":true,"dist":{"shasum":"63ecaf7eb9544019dafdf0798e8480fb3865852b","tarball":"https://registry.npmjs.org/cluster/-/cluster-0.7.0.tgz"},"scripts":{},"maintainers":[{"name":"tjholowaychuk","email":"tj@vision-media.ca"}],"directories":{}},"0.7.1":{"name":"cluster","description":"extensible multi-core server manager","keywords":["server","spark","fugue","tcp","workers"],"version":"0.7.1","homepage":"http://learnboost.github.com/cluster","repository":{"type":"git","url":"git://github.com/LearnBoost/cluster.git"},"author":{"name":"TJ Holowaychuk","email":"tj@learnboost.com","url":"http://tjholowaychuk.com"},"main":"index","dependencies":{"log":">= 1.2.0","mkdirp":">= 0.0.1"},"devDependencies":{"should":"0.2.x"},"engines":{"node":"*"},"_npmJsonOpts":{"file":"/Users/tj/.npm/cluster/0.7.1/package/package.json","wscript":false,"contributors":false,"serverjs":false},"_id":"cluster@0.7.1","_engineSupported":true,"_npmVersion":"1.0.24","_nodeVersion":"v0.4.10","_defaultsLoaded":true,"dist":{"shasum":"5d86c81e37719e3ee9977d4a182d080e8753cb28","tarball":"https://registry.npmjs.org/cluster/-/cluster-0.7.1.tgz"},"scripts":{},"maintainers":[{"name":"tjholowaychuk","email":"tj@vision-media.ca"}],"directories":{}},"0.7.2":{"name":"cluster","description":"extensible multi-core server manager","keywords":["server","spark","fugue","tcp","workers"],"version":"0.7.2","homepage":"http://learnboost.github.com/cluster","repository":{"type":"git","url":"git://github.com/LearnBoost/cluster.git"},"author":{"name":"TJ Holowaychuk","email":"tj@learnboost.com","url":"http://tjholowaychuk.com"},"main":"index","dependencies":{"log":">= 1.2.0","mkdirp":">= 0.0.1"},"devDependencies":{"should":"0.2.x"},"engines":{"node":"*"},"_npmJsonOpts":{"file":"/Users/tj/.npm/cluster/0.7.2/package/package.json","wscript":false,"contributors":false,"serverjs":false},"_id":"cluster@0.7.2","_engineSupported":true,"_npmVersion":"1.0.24","_nodeVersion":"v0.4.11","_defaultsLoaded":true,"dist":{"shasum":"d7b41fec7a1eaae7fab06d86416c011b30b97272","tarball":"https://registry.npmjs.org/cluster/-/cluster-0.7.2.tgz"},"scripts":{},"maintainers":[{"name":"tjholowaychuk","email":"tj@vision-media.ca"}],"directories":{}},"0.7.3":{"name":"cluster","description":"extensible multi-core server manager","keywords":["server","spark","fugue","tcp","workers"],"version":"0.7.3","homepage":"http://learnboost.github.com/cluster","repository":{"type":"git","url":"git://github.com/LearnBoost/cluster.git"},"author":{"name":"TJ Holowaychuk","email":"tj@learnboost.com","url":"http://tjholowaychuk.com"},"main":"index","dependencies":{"log":">= 1.2.0","mkdirp":">= 0.0.1"},"devDependencies":{"should":"0.2.x"},"engines":{"node":"*"},"_npmJsonOpts":{"file":"/Users/tj/.npm/cluster/0.7.3/package/package.json","wscript":false,"contributors":false,"serverjs":false},"_id":"cluster@0.7.3","_engineSupported":true,"_npmVersion":"1.0.24","_nodeVersion":"v0.4.11","_defaultsLoaded":true,"dist":{"shasum":"037c409c84f543ffe3e443c288272743f92092d9","tarball":"https://registry.npmjs.org/cluster/-/cluster-0.7.3.tgz"},"scripts":{},"maintainers":[{"name":"tjholowaychuk","email":"tj@vision-media.ca"}],"directories":{}},"0.7.4":{"name":"cluster","description":"extensible multi-core server manager","keywords":["server","spark","fugue","tcp","workers"],"version":"0.7.4","homepage":"http://learnboost.github.com/cluster","repository":{"type":"git","url":"git://github.com/LearnBoost/cluster.git"},"author":{"name":"TJ Holowaychuk","email":"tj@learnboost.com","url":"http://tjholowaychuk.com"},"main":"index","dependencies":{"log":">= 1.2.0","mkdirp":">= 0.0.1"},"devDependencies":{"should":"0.2.x"},"engines":{"node":"*"},"_npmJsonOpts":{"file":"/Users/tj/.npm/cluster/0.7.4/package/package.json","wscript":false,"contributors":false,"serverjs":false},"_id":"cluster@0.7.4","_engineSupported":true,"_npmVersion":"1.0.24","_nodeVersion":"v0.4.11","_defaultsLoaded":true,"dist":{"shasum":"7fa642d31d550ba48c5bd3693314756190edd707","tarball":"https://registry.npmjs.org/cluster/-/cluster-0.7.4.tgz"},"scripts":{},"maintainers":[{"name":"tjholowaychuk","email":"tj@vision-media.ca"}],"directories":{}},"0.7.5":{"name":"cluster","description":"extensible multi-core server manager","keywords":["server","spark","fugue","tcp","workers"],"version":"0.7.5","homepage":"http://learnboost.github.com/cluster","repository":{"type":"git","url":"git://github.com/LearnBoost/cluster.git"},"author":{"name":"TJ Holowaychuk","email":"tj@learnboost.com","url":"http://tjholowaychuk.com"},"main":"index","dependencies":{"log":">= 1.2.0","mkdirp":">= 0.0.1"},"devDependencies":{"should":"0.2.x"},"engines":{"node":"*"},"_npmJsonOpts":{"file":"/Users/tj/.npm/cluster/0.7.5/package/package.json","wscript":false,"contributors":false,"serverjs":false},"_id":"cluster@0.7.5","_engineSupported":true,"_npmVersion":"1.0.24","_nodeVersion":"v0.4.12","_defaultsLoaded":true,"dist":{"shasum":"ceb3e4601ba17fbb06952c9b465ce6d14e486e59","tarball":"https://registry.npmjs.org/cluster/-/cluster-0.7.5.tgz"},"scripts":{},"maintainers":[{"name":"tjholowaychuk","email":"tj@vision-media.ca"}],"directories":{}},"0.7.6":{"name":"cluster","description":"extensible multi-core server manager","keywords":["server","spark","fugue","tcp","workers"],"version":"0.7.6","homepage":"http://learnboost.github.com/cluster","repository":{"type":"git","url":"git://github.com/LearnBoost/cluster.git"},"author":{"name":"TJ Holowaychuk","email":"tj@learnboost.com","url":"http://tjholowaychuk.com"},"main":"index","dependencies":{"log":">= 1.2.0","mkdirp":">= 0.0.1"},"devDependencies":{"should":"0.2.x"},"engines":{"node":"*"},"_npmJsonOpts":{"file":"/Users/tj/.npm/cluster/0.7.6/package/package.json","wscript":false,"contributors":false,"serverjs":false},"_id":"cluster@0.7.6","_engineSupported":true,"_npmVersion":"1.0.24","_nodeVersion":"v0.4.12","_defaultsLoaded":true,"dist":{"shasum":"645cec9c00561f5534f4a7e34db833ea75f73a53","tarball":"https://registry.npmjs.org/cluster/-/cluster-0.7.6.tgz"},"scripts":{},"maintainers":[{"name":"tjholowaychuk","email":"tj@vision-media.ca"}],"directories":{}},"0.7.7":{"name":"cluster","description":"extensible multi-core server manager","keywords":["server","spark","fugue","tcp","workers"],"version":"0.7.7","homepage":"http://learnboost.github.com/cluster","repository":{"type":"git","url":"git://github.com/LearnBoost/cluster.git"},"author":{"name":"TJ Holowaychuk","email":"tj@learnboost.com","url":"http://tjholowaychuk.com"},"main":"index","dependencies":{"log":">= 1.2.0","mkdirp":">= 0.0.1"},"devDependencies":{"should":"0.2.x"},"engines":{"node":"*"},"_npmJsonOpts":{"file":"/Users/tj/.npm/cluster/0.7.7/package/package.json","wscript":false,"contributors":false,"serverjs":false},"_id":"cluster@0.7.7","_engineSupported":true,"_npmVersion":"1.0.24","_nodeVersion":"v0.4.12","_defaultsLoaded":true,"dist":{"shasum":"e497e267cc956bd0b0513adb4aa393357d0085ef","tarball":"https://registry.npmjs.org/cluster/-/cluster-0.7.7.tgz"},"scripts":{},"maintainers":[{"name":"tjholowaychuk","email":"tj@vision-media.ca"}],"directories":{}}},"maintainers":[{"name":"segment-admin","email":"tools+npm@segment.com"},{"name":"tjholowaychuk","email":"tj@vision-media.ca"}],"time":{"modified":"2016-08-15T18:36:17.276Z","created":"2011-02-16T01:47:41.650Z","0.0.1":"2011-02-16T01:47:42.097Z","0.0.2":"2011-02-16T02:00:53.588Z","0.0.3":"2011-02-16T15:44:37.107Z","0.0.4":"2011-02-17T21:29:22.383Z","0.1.0":"2011-02-18T18:57:22.624Z","0.1.1":"2011-02-19T00:09:37.104Z","0.2.0":"2011-02-21T17:04:17.624Z","0.2.1":"2011-02-21T17:49:23.855Z","0.2.2":"2011-02-22T01:52:15.804Z","0.2.3":"2011-02-22T02:54:47.404Z","0.2.4":"2011-02-25T17:47:40.733Z","0.3.0":"2011-02-28T19:42:05.040Z","0.3.1":"2011-03-01T01:56:22.837Z","0.3.2":"2011-03-01T20:20:01.360Z","0.3.3":"2011-03-03T23:10:40.847Z","0.4.0":"2011-03-08T17:33:16.608Z","0.4.1":"2011-03-10T19:18:31.765Z","0.4.2":"2011-03-15T23:10:04.404Z","0.5.0":"2011-03-24T19:00:15.895Z","0.5.1":"2011-03-24T21:49:14.236Z","0.5.2":"2011-03-25T15:59:59.230Z","0.5.3":"2011-03-30T19:30:56.971Z","0.5.4":"2011-04-05T23:42:08.537Z","0.5.5":"2011-04-06T00:08:59.690Z","0.5.6":"2011-04-16T00:51:59.200Z","0.5.7":"2011-04-18T04:57:18.472Z","0.6.0":"2011-04-19T00:29:49.556Z","0.6.1":"2011-04-26T15:33:01.263Z","0.6.2":"2011-05-11T18:14:40.426Z","0.6.3":"2011-06-11T17:39:06.965Z","0.6.4":"2011-06-15T00:04:11.770Z","0.6.5":"2011-07-18T19:11:42.838Z","0.6.6":"2011-07-18T22:18:10.847Z","0.6.7":"2011-07-19T12:34:26.809Z","0.6.8":"2011-07-19T13:40:26.467Z","0.6.9":"2011-07-20T17:22:52.559Z","0.7.0":"2011-08-16T04:25:44.617Z","0.7.1":"2011-08-18T16:02:06.103Z","0.7.2":"2011-09-12T16:41:04.650Z","0.7.3":"2011-09-12T18:31:04.350Z","0.7.4":"2011-09-19T17:50:06.289Z","0.7.5":"2011-09-23T17:04:50.204Z","0.7.6":"2011-10-03T22:38:36.013Z","0.7.7":"2011-10-04T20:10:46.599Z"},"author":{"name":"TJ Holowaychuk","email":"tj@learnboost.com","url":"http://tjholowaychuk.com"},"repository":{"type":"git","url":"git://github.com/LearnBoost/cluster.git"},"users":{"pid":true,"joliva":true,"andrewshell":true,"agent_9191":true,"majgis":true,"adamlu":true,"ahsanshafiq":true},"homepage":"http://learnboost.github.com/cluster","keywords":["server","spark","fugue","tcp","workers"],"readme":"","readmeFilename":"","_attachments":{},"_etag":"\"7OD5MR47MQL3JJA6QWH7JQBYN\""}